CHANGES.rst
CONTRIBUTORS.rst
MANIFEST.in
README.rst
requirements.txt
setup.cfg
setup.py
collective/__init__.py
collective.autopublishing.egg-info/PKG-INFO
collective.autopublishing.egg-info/SOURCES.txt
collective.autopublishing.egg-info/dependency_links.txt
collective.autopublishing.egg-info/entry_points.txt
collective.autopublishing.egg-info/namespace_packages.txt
collective.autopublishing.egg-info/not-zip-safe
collective.autopublishing.egg-info/requires.txt
collective.autopublishing.egg-info/top_level.txt
collective/autopublishing/__init__.py
collective/autopublishing/behavior.py
collective/autopublishing/configure.zcml
collective/autopublishing/eventhandler.py
collective/autopublishing/interfaces.py
collective/autopublishing/profiles.zcml
collective/autopublishing/setuphandlers.py
collective/autopublishing/upgradesteps.py
collective/autopublishing/upgradesteps.zcml
collective/autopublishing/browser/__init__.py
collective/autopublishing/browser/autopublish_report.pt
collective/autopublishing/browser/autopublishreport.py
collective/autopublishing/browser/autopublishsettings.py
collective/autopublishing/browser/configure.zcml
collective/autopublishing/browser/controlpanel_layout.pt
collective/autopublishing/locales/collective.autopublishing.pot
collective/autopublishing/locales/plone.pot
collective/autopublishing/locales/update.sh
collective/autopublishing/locales/da/LC_MESSAGES/collective.autopublishing.po
collective/autopublishing/locales/da/LC_MESSAGES/plone.po
collective/autopublishing/locales/de/LC_MESSAGES/collective.autopublishing.po
collective/autopublishing/locales/de/LC_MESSAGES/plone.po
collective/autopublishing/locales/es/LC_MESSAGES/collective.autopublishing.po
collective/autopublishing/locales/fr/LC_MESSAGES/collective.autopublishing.po
collective/autopublishing/locales/fr/LC_MESSAGES/plone.po
collective/autopublishing/profiles/default/browserlayer.xml
collective/autopublishing/profiles/default/collective.autopublishing_various.txt
collective/autopublishing/profiles/default/controlpanel.xml
collective/autopublishing/profiles/default/metadata.xml
collective/autopublishing/profiles/default/registry.xml
collective/autopublishing/profiles/default/rolemap.xml
collective/autopublishing/profiles/default/types/Collection.xml
collective/autopublishing/profiles/default/types/Document.xml
collective/autopublishing/profiles/default/types/Event.xml
