Metadata-Version: 2.1
Name: collective.autopublishing
Version: 1.0.3
Summary: Publishes and retracts on effective or expired dates.
Home-page: http://pypi.python.org/pypi/collective.autopublishing
Author: Mustapha Benali
Author-email: mustapha@headnet.dk
License: GPLv2+
Keywords: plone workflow publishing
Platform: UNKNOWN
Classifier: Framework :: Plone
Classifier: Framework :: Plone :: 5.0
Classifier: Framework :: Plone :: 5.1
Classifier: Framework :: Zope2
Classifier: Programming Language :: Python
Classifier: Programming Language :: Python :: 2.7
Provides-Extra: test
